README.md
setup.py
argparse_dataclasses/__init__.py
argparse_dataclasses/boilerplate.py
argparse_dataclasses.egg-info/PKG-INFO
argparse_dataclasses.egg-info/SOURCES.txt
argparse_dataclasses.egg-info/dependency_links.txt
argparse_dataclasses.egg-info/top_level.txt