Metadata-Version: 2.1
Name: argparse-dataclasses
Version: 0.1.1
Summary: UNKNOWN
Home-page: UNKNOWN
Author: Felix Neko
Author-email: felix-neko@list.ru
License: UNKNOWN
Platform: UNKNOWN
